jinjer2.py
setup.py
Jinjer2.egg-info/PKG-INFO
Jinjer2.egg-info/SOURCES.txt
Jinjer2.egg-info/dependency_links.txt
Jinjer2.egg-info/entry_points.txt
Jinjer2.egg-info/requires.txt
Jinjer2.egg-info/top_level.txt